{"0": {"relations": [["Recognition of proper nouns", "proper nouns", "FEATURE-OF"], ["Recognition of proper nouns", "Japanese text", "USED-FOR"], ["morphological analysis", "Japanese text processing", "PART-OF"], ["Recognition of proper nouns", "morphological analysis", "PART-OF"]]}, "1": {"relations": [["It", "Japanese information extraction", "USED-FOR"]]}, "2": {"relations": [["approach", "Multi-lingual Evaluation Task MET", "USED-FOR"], ["Multi-lingual Evaluation Task MET", "morphological analysis problem", "HYPONYM-OF"], ["morphological analysis problem", "Japanese text", "FEATURE-OF"]]}, "3": {"relations": [["morphological analyzer", "recognition and classification of proper names , numerical and temporal expressions", "USED-FOR"], ["proper names , numerical and temporal expressions", "Named Entity NE items", "HYPONYM-OF"], ["recognition and classification of proper names , numerical and temporal expressions", "Named Entity NE items", "FEATURE-OF"], ["morphological analyzer", "Japanese text", "USED-FOR"]]}, "4": {"relations": [["analyzer", "`` Amorph ''", "EQUAL-TO"]]}, "5": {"relations": [["Amorph", "NE items", "USED-FOR"], ["dictionary lookup", "Amorph", "PART-OF"], ["rule application", "Amorph", "PART-OF"]]}, "6": {"relations": [["it", "dictionaries", "USED-FOR"], ["it", "Japanese character strings", "USED-FOR"]]}, "7": {"relations": [["dictionary lookup stage", "rules", "USED-FOR"], ["rules", "NE items", "USED-FOR"]]}, "8": {"relations": []}, "9": {"relations": [["priori geometric constraints", "3 -- D stereo reconstruction scheme", "USED-FOR"], ["image information", "3 -- D stereo reconstruction scheme", "USED-FOR"], ["3 -- D stereo reconstruction scheme", "3 -- D shape", "USED-FOR"]]}, "10": {"relations": [["approach", "iterative deformation of a 3 -- D surface mesh", "USED-FOR"], ["iterative deformation of a 3 -- D surface mesh", "objective function", "USED-FOR"]]}, "11": {"relations": [["anisotropic meshing", "non-quadratic approach", "CONJUNCTION"], ["anisotropic meshing", "regularization", "USED-FOR"], ["non-quadratic approach", "regularization", "USED-FOR"], ["reconstruction", "triangulations", "FEATURE-OF"], ["vertices", "triangulations", "PART-OF"]]}, "12": {"relations": [["Structural or numerical constraints", "reconstruction process", "USED-FOR"], ["constrained optimization scheme", "reconstruction process", "PART-OF"]]}, "13": {"relations": [["They", "reconstruction", "USED-FOR"], ["reconstruction", "priori knowledge", "USED-FOR"], ["consistency", "object shape", "FEATURE-OF"]]}}